pyzam/__init__.py
pyzam/__main__.py
pyzam/identify.py
pyzam/record.py
pyzam/data/default_album_cover.png
pyzam-0.13.2.dist-info/licenses/LICENSE.txt
pyzam-0.13.2.dist-info/METADATA
pyzam-0.13.2.dist-info/WHEEL
pyzam-0.13.2.dist-info/entry_points.txt
pyzam-0.13.2.dist-info/top_level.txt
pyzam-0.13.2.dist-info/RECORD
