Metadata-Version: 2.4
Name: Pyzam
Version: 0.13.2
Summary: Recognize and Visualize Songs in Your CLI
Home-page: https://github.com/lukafilipxvic/Pyzam
Author: lukafilipxvic
Requires-Python: >=3.9
License-File: LICENSE.txt
Requires-Dist: climage>=0.2.2
Requires-Dist: numpy<=2.2.6
Requires-Dist: requests>=2.32.3
Requires-Dist: rich>=14.0.0
Requires-Dist: setuptools<81.0.0
Requires-Dist: shazamio>=0.8.0
Requires-Dist: soundcard>=0.4.4
Requires-Dist: soundfile>=0.13.1
Provides-Extra: api
Requires-Dist: fastapi>=0.115.12; extra == "api"
Dynamic: author
Dynamic: home-page
Dynamic: license-file
Dynamic: requires-python
